ai4privacy/__init__.py
ai4privacy/mask.py
ai4privacy-0.1.2.dist-info/licenses/LICENSE
ai4privacy-0.1.2.dist-info/METADATA
ai4privacy-0.1.2.dist-info/WHEEL
ai4privacy-0.1.2.dist-info/top_level.txt
ai4privacy-0.1.2.dist-info/RECORD
